marcussays/__init__.py
marcussays/main.py
marcussays-0.1.0.dist-info/METADATA
marcussays-0.1.0.dist-info/WHEEL
marcussays-0.1.0.dist-info/top_level.txt
marcussays-0.1.0.dist-info/RECORD
