Metadata-Version: 2.2
Name: marcussays
Version: 0.1.0
Summary: A fun and simple module by Marcus
Author: Marcus McCrea
Classifier: Programming Language :: Python :: 3
Classifier: License :: OSI Approved :: MIT License
Classifier: Operating System :: OS Independent
Requires-Python: >=3.6
Dynamic: author
Dynamic: classifier
Dynamic: description
Dynamic: description-content-type
Dynamic: requires-python
Dynamic: summary
